{"cameraMode":{"drawMode":0,"name":"Shaded","section":"Shading Mode"},"sceneLighting":true,"audioPlay":false,"sceneViewState":{"showFog":true,"showMaterialUpdate":false,"showSkybox":true,"showFlares":true,"showImageEffects":true,"showParticleSystems":true},"in2DMode":false,"pivot":{"x":-5.579868316650391,"y":19.076744079589845,"z":15.91097640991211},"rotation":{"x":0.24142120778560639,"y":-0.027515076100826265,"z":0.007116435561329126,"w":0.9701668620109558},"size":28.13544273376465,"orthographic":false}