{"cameraMode":{"drawMode":0,"name":"Shaded","section":"Shading Mode"},"sceneLighting":true,"audioPlay":false,"sceneViewState":{"showFog":true,"showMaterialUpdate":false,"showSkybox":true,"showFlares":true,"showImageEffects":true,"showParticleSystems":true},"in2DMode":false,"pivot":{"x":-0.8688256740570068,"y":35.742706298828128,"z":-14.266117095947266},"rotation":{"x":-0.4916880130767822,"y":0.00025245288270525634,"z":-0.00013076889445073903,"w":-0.8710312843322754},"size":21.488994598388673,"orthographic":false}